deepdrive_api/__init__.py
deepdrive_api/client.py
deepdrive_api/constants.py
deepdrive_api/logs.py
deepdrive_api/methods.py
deepdrive_api/run_command.py
deepdrive_api/server.py
deepdrive_api/simple_pair_server.py
deepdrive_api/utils.py
deepdrive_api-3.1.20200301311111.dist-info/LICENSE
deepdrive_api-3.1.20200301311111.dist-info/METADATA
deepdrive_api-3.1.20200301311111.dist-info/WHEEL
deepdrive_api-3.1.20200301311111.dist-info/top_level.txt
deepdrive_api-3.1.20200301311111.dist-info/zip-safe
deepdrive_api-3.1.20200301311111.dist-info/RECORD
