Metadata-Version: 2.1
Name: deepdrive-api
Version: 3.1.20200301311111
Summary: Deepdrive API used to run agents over the network
Home-page: http://github.com/deepdrive/deepdrive-api
Author: Deepdrive
Author-email: craig@deepdrive.io
License: MIT
Keywords: deepdrive api
Platform: UNKNOWN
Classifier: License :: OSI Approved :: MIT License
Classifier: Programming Language :: Python :: 3.5
Classifier: Programming Language :: Python :: 3.6
Classifier: Programming Language :: Python :: 3.7
Classifier: Environment :: Console
Requires-Python: >=3.5
Requires-Dist: setuptools (>=38.6.0)
Requires-Dist: twine (>=1.11.0)
Requires-Dist: pyarrow (==0.12.1)
Requires-Dist: pyzmq
Requires-Dist: future
Requires-Dist: gym (==0.10.0)
Requires-Dist: numpy (>=1.16.1)
Requires-Dist: wheel (>=0.31.0)
